nohtpy/__init__.py
nohtpy/utils/__init__.py
nohtpy/utils/common_utils.py
nohtpy/utils/password_utils.py
nohtpy-0.1.0.dist-info/METADATA
nohtpy-0.1.0.dist-info/WHEEL
nohtpy-0.1.0.dist-info/RECORD
