Metadata-Version: 2.3
Name: nohtpy
Version: 0.1.0
Summary: 
Author: amiter
Author-email: amiter@yeah.net
Requires-Python: >=3.9.6,<3.12
Classifier: Programming Language :: Python :: 3
Classifier: Programming Language :: Python :: 3.10
Classifier: Programming Language :: Python :: 3.11
Requires-Dist: poetry (>=2.0.0,<3.0.0)
Requires-Dist: pycryptodome (>=3.20.0,<4.0.0)
